<annotation>
	<folder>train</folder>
	<filename>2024-0420-0248-22-307_type8_No0000_OK.jpg</filename>
	<path>C:\Users\lilia\Documents\TPP\Código GIT\Aux for labeling\5-clases\tres\train\2024-0420-0248-22-307_type8_No0000_OK.jpg</path>
	<source>
		<database>Unknown</database>
	</source>
	<size>
		<width>1920</width>
		<height>1080</height>
		<depth>3</depth>
	</size>
	<segmented>0</segmented>
	<object>
		<name>grande</name>
		<pose>Unspecified</pose>
		<truncated>0</truncated>
		<difficult>0</difficult>
		<bndbox>
			<xmin>442</xmin>
			<ymin>729</ymin>
			<xmax>665</xmax>
			<ymax>950</ymax>
		</bndbox>
	</object>
	<object>
		<name>mediano</name>
		<pose>Unspecified</pose>
		<truncated>0</truncated>
		<difficult>0</difficult>
		<bndbox>
			<xmin>924</xmin>
			<ymin>500</ymin>
			<xmax>1034</xmax>
			<ymax>614</ymax>
		</bndbox>
	</object>
	<object>
		<name>chico</name>
		<pose>Unspecified</pose>
		<truncated>0</truncated>
		<difficult>0</difficult>
		<bndbox>
			<xmin>1219</xmin>
			<ymin>129</ymin>
			<xmax>1286</xmax>
			<ymax>195</ymax>
		</bndbox>
	</object>
	<object>
		<name>capo</name>
		<pose>Unspecified</pose>
		<truncated>1</truncated>
		<difficult>0</difficult>
		<bndbox>
			<xmin>1040</xmin>
			<ymin>202</ymin>
			<xmax>1920</xmax>
			<ymax>1080</ymax>
		</bndbox>
	</object>
</annotation>
